dna_segmentation_benchmark/evaluate_predictors.py
dna_segmentation_benchmark/file_reader.py
dna_segmentation_benchmark/label_definition.py
dna_segmentation_benchmark/single_pred_plotting.py
dna_segmentation_benchmark/summary_stat_plotting.py
dna_segmentation_benchmark/icons/exon_deletion.png
dna_segmentation_benchmark/icons/exon_insertion.png
dna_segmentation_benchmark/icons/joined_exons.png
dna_segmentation_benchmark/icons/left_deletion.png
dna_segmentation_benchmark/icons/left_extension.png
dna_segmentation_benchmark/icons/right_deletion.png
dna_segmentation_benchmark/icons/right_extension.png
dna_segmentation_benchmark/icons/split_exons.png
dna_segmentation_benchmark-0.0.4.dist-info/METADATA
dna_segmentation_benchmark-0.0.4.dist-info/WHEEL
dna_segmentation_benchmark-0.0.4.dist-info/top_level.txt
dna_segmentation_benchmark-0.0.4.dist-info/RECORD
