Metadata-Version: 2.4
Name: dna-segmentation-benchmark
Version: 0.0.4
Summary: A collection of different evaluators for dna nucleodtide level labeling
Project-URL: Source Code, https://github.com/PredictProtein/benchmark
Requires-Python: >=3.10
Requires-Dist: biopython>=1.85
Requires-Dist: bokeh>=3.7.0
Requires-Dist: h5py>=3.13.0
Requires-Dist: matplotlib>=3.10.1
Requires-Dist: numpy>=2.2.4
Requires-Dist: pandas>=2.2.3
Requires-Dist: pytest>=8.3.5
Requires-Dist: scikit-learn>=1.6.1
Requires-Dist: seaborn>=0.13.2
Requires-Dist: tqdm>=4.67.1
